eventiq_msgpack/__about__.py
eventiq_msgpack/__init__.py
eventiq_msgpack/decoder.py
eventiq_msgpack/encoder.py
eventiq_msgpack/py.typed
eventiq_msgpack-0.2.0.dist-info/METADATA
eventiq_msgpack-0.2.0.dist-info/WHEEL
eventiq_msgpack-0.2.0.dist-info/licenses/LICENSE
eventiq_msgpack-0.2.0.dist-info/RECORD
